common_sense/__init__.py
common_sense/ai.py
common_sense/dates.py
common_sense/debug.py
common_sense/devtools.py
common_sense/files.py
common_sense/jokes.py
common_sense/life.py
common_sense/lists.py
common_sense/net.py
common_sense/numbers.py
common_sense/philosophy.py
common_sense/strings.py
common_sense/utils.py
common_sense/wisdom.py
common_sense-0.1.0.dist-info/licenses/LICENSE
common_sense-0.1.0.dist-info/METADATA
common_sense-0.1.0.dist-info/WHEEL
common_sense-0.1.0.dist-info/top_level.txt
common_sense-0.1.0.dist-info/RECORD
