Metadata-Version: 2.4
Name: common-sense
Version: 0.1.0
Summary: Because common sense is not so common. Now it is — in Python!
Home-page: https://github.com/Happy-Kumar-Sharma/common-sense
Author: Happy Sharma
Author-email: happycse54@gmail.com
License: MIT
Classifier: Programming Language :: Python :: 3
Classifier: License :: OSI Approved :: MIT License
Classifier: Operating System :: OS Independent
Requires-Python: >=3.7
License-File: LICENSE
Requires-Dist: pytest
Requires-Dist: shutil; python_version < "3.8"
Requires-Dist: requests
Requires-Dist: urllib3
Dynamic: author
Dynamic: author-email
Dynamic: classifier
Dynamic: description
Dynamic: description-content-type
Dynamic: home-page
Dynamic: license
Dynamic: license-file
Dynamic: requires-dist
Dynamic: requires-python
Dynamic: summary
